{
  "id": "com.bluepants.borgwarehouse",
  "title": "Borg Warehouse",
  "author": "Shaun Sundquist <shaun@bluepants.dev>",
  "description": "Borg Warehouse",
  "tagline": "Web UI for BorgBackup repositories",
  "version": "3.1.2-1",
  "healthCheckPath": "/",
  "httpPort": 3000,
  "tcpPorts": {
    "SSH_SERVER_PORT": {
      "title": "SSH Port",
      "description": "SSH endpoint used by Borg clients",
      "defaultValue": 2222,
      "containerPort": 22,
      "enabledByDefault": true
    }
  },
  "addons": {
    "localstorage": {}
  },
  "manifestVersion": 2,
  "website": "https://bluepants.dev",
  "contactEmail": "support@bluepants.dev",
  "icon": "file://borgwarehouse-logo.png",
  "tags": [ "test", "collaboration" ],
  "mediaLinks": [ "https://images.rapgenius.com/fd0175ef780e2feefb30055be9f2e022.520x343x1.jpg" ]
}